m2controller/__init__.py
m2controller/bleDataDecoder.py
m2controller/constShared.py
m2controller/m2Const.py
m2controller/m2controller.py
m2controller/mqttutils.py
m2controller/readimage.py
m2controller/scan.py
m2controller/telemetrySocketListeningServer.py
m2controller/utils.py
m2controller/binaryHelper/blescanRPi
m2controller/binaryHelper/blescan_x86_64
m2controller/binaryHelper/readme.txt
m2controller/examples/__init__.py
m2controller/examples/functionTest.py
m2controller/examples/ledMatrixAnimation.py
m2controller/examples/ledmatrix_tutorial1_internetAnimationCtrl.py
m2controller/examples/ledmatrix_tutorial1_internetCtrl.py
m2controller/examples/ledmatrix_tutorial2_directCtrl.py
m2controller/examples/ledmatrix_tutorial3_BridgeCtrl.py
m2controller/examples/ledmatrix_tutorial3_BridgeCtrlGeneralDevices.py
m2controller/examples/ledmatrix_tutorial4_internetMultiCtrl.py
m2controller/examples/microscope_tutorial1.py
m2controller/examples/microscope_tutorial2_autoHome.py
m2controller/examples/microscope_tutorial3_autoHome.py
m2controller/examples/pacman0.ico
m2controller/examples/pacman1.ico
m2controller/examples/pendulum1.py
m2controller/examples/pendulum2.py
m2controller/examples/plane_tutorial1.py
m2controller/examples/plant_care_tutorial1_relativeTime.py
m2controller/examples/plant_care_tutorial2_absoluteTime.py
m2controller/examples/security_tutorial1.py
m2controller/examples/spider_tutorial1.py
m2controller/examples/spider_tutorial2_intranetCtrl.py
m2controller/examples/spider_tutorial3_internetCtrl.py
m2controller/examples/spider_tutorial4_absoluteOrientation.py
m2controller/examples/thunderstorm_tutorial1.py
m2controller/examples/usrCfg.py
m2controller-0.2.1.dist-info/LICENSE
m2controller-0.2.1.dist-info/METADATA
m2controller-0.2.1.dist-info/WHEEL
m2controller-0.2.1.dist-info/top_level.txt
m2controller-0.2.1.dist-info/RECORD
