Metadata-Version: 2.1
Name: m2controller
Version: 0.2.1
Summary: an SDK for educational robotics
Home-page: https://github.com/dronedevelopers/m2controller/tree/master/pySDK
Author: drone developer
Author-email: dronedeveloper@gmail.com
License: UNKNOWN
Platform: UNKNOWN
Classifier: Programming Language :: Python :: 3
Classifier: License :: OSI Approved :: MIT License
Classifier: Operating System :: OS Independent
